mcp_server_database/__init__.py
mcp_server_database/__main__.py
mcp_server_database/server.py
mcp_server_database/test.py
mcp_server_database/utils.py
mcp_server_database/agent/__init__.py
mcp_server_database/agent/base.py
mcp_server_database/agent/engine.py
mcp_server_database/agent/llm.py
mcp_server_database/agent/prompt.py
mcp_server_database/agent/react.py
mcp_server_database/agent/schema.py
mcp_server_database-0.1.4.dist-info/METADATA
mcp_server_database-0.1.4.dist-info/WHEEL
mcp_server_database-0.1.4.dist-info/entry_points.txt
mcp_server_database-0.1.4.dist-info/top_level.txt
mcp_server_database-0.1.4.dist-info/RECORD
