Metadata-Version: 2.4
Name: mcp-server-database
Version: 0.1.4
Summary: 将自然语言转化为sql语句
Requires-Python: >=3.12
Requires-Dist: mcp>=1.6.0
Requires-Dist: openai>=1.76.0
Requires-Dist: oracledb>=3.1.0
Requires-Dist: psycopg2-binary>=2.9.10
Requires-Dist: pymssql>=2.3.4
Requires-Dist: pymysql>=1.1.1
Requires-Dist: python-dotenv>=1.1.0
Requires-Dist: sqlalchemy>=2.0.40
